{
  "phase": 14.8,
  "name": "Archetype Selection Algorithm",
  "step": 4,
  "step_name": "execute",
  "step_label": "Implementing tasks",
  "status": "active",
  "tasks_total": 5,
  "tasks_done": 0,
  "current_task": "T1 — Add structural families and affinity scoring table",
  "tests_written": 0,
  "tests_passing": 0,
  "commits": 0,
  "errors": [],
  "warnings": [],
  "started_at": "2026-03-30T15:32:43Z",
  "updated_at": "2026-03-30T15:32:43Z",
  "history": [{"step":1,"name":"setup","label":"Setup & sync","at":"2026-03-30T15:32:43Z","status":"done"},{"step":2,"name":"health_check","label":"Code health check","at":"2026-03-30T15:32:43Z","status":"done"},{"step":3,"name":"plan","label":"Writing implementation plan","at":"2026-03-30T15:32:43Z","status":"done"},{"step":3.5,"name":"tdd","label":"Writing failing tests (TDD)","at":"2026-03-30T15:32:43Z","status":"skipped"}]
}
